django_kc_auth/__init__.py
django_kc_auth/apps.py
django_kc_auth/backends.py
django_kc_auth/keycloak_openid_config.py
django_kc_auth/middleware.py
django_kc_auth/models.py
django_kc_auth/signals.py
django_kc_auth/urls.py
django_kc_auth/views.py
django_kc_auth/management/commands/add_permissions.py
django_kc_auth/migrations/0001_initial.py
django_kc_auth/migrations/__init__.py
django_kc_auth/templatetags/kc_auth_filters.py
django_kc_auth-0.0.8.dist-info/METADATA
django_kc_auth-0.0.8.dist-info/WHEEL
django_kc_auth-0.0.8.dist-info/top_level.txt
django_kc_auth-0.0.8.dist-info/RECORD
