Metadata-Version: 2.4
Name: django-kc-auth
Version: 0.0.8
Summary: A comprehensive Django package for Keycloak authentication integration, providing seamless SSO, session management, and user synchronization between Django and Keycloak.
Author-email: Juraj Perić <juraj.peric@gmail.com>
License: MIT
Project-URL: Homepage, https://github.com/perkeje/django-kc-auth
Project-URL: Issues, https://github.com/perkeje/django-kc-auth/issues
Keywords: django,keycloak,authentication,sso,session-management
Classifier: Framework :: Django
Classifier: Intended Audience :: Developers
Classifier: License :: OSI Approved :: MIT License
Classifier: Programming Language :: Python :: 3
Classifier: Programming Language :: Python :: 3.8
Classifier: Programming Language :: Python :: 3.9
Classifier: Programming Language :: Python :: 3.10
Classifier: Programming Language :: Python :: 3.11
Classifier: Programming Language :: Python :: 3.12
Classifier: Programming Language :: Python :: 3.13
Classifier: Topic :: Software Development :: Libraries :: Python Modules
Classifier: Topic :: System :: Systems Administration :: Authentication/Directory
Requires-Python: >=3.10
Requires-Dist: Django>=5.0.1
Requires-Dist: djangorestframework>=3.15.2
Requires-Dist: python-keycloak>=4.5.0
Requires-Dist: jwt>=1.3.1
